tussik/email/Emailer.py
tussik/email/__init__.py
tussik.email-0.1.0rc1.dist-info/LICENSE
tussik.email-0.1.0rc1.dist-info/METADATA
tussik.email-0.1.0rc1.dist-info/WHEEL
tussik.email-0.1.0rc1.dist-info/top_level.txt
tussik.email-0.1.0rc1.dist-info/zip-safe
tussik.email-0.1.0rc1.dist-info/RECORD
