Metadata-Version: 2.1
Name: tussik.email
Version: 0.1.0rc1
Summary: Tussik Emailer
Home-page: https://github.com/tussikcom/tussik-email
Author: Darren Martz
Author-email: darren@tussik.com
License: MIT
Project-URL: Issue Tracker, https://github.com/tussikcom/tussik-email/issues
Project-URL: Documentation, https://github.com/tussikcom/tussik-email
Project-URL: home-page, https://github.com/tussikcom/tussik-email
Keywords: smtp,email,tussik
Classifier: Development Status :: 5 - Production/Stable
Classifier: Intended Audience :: Developers
Classifier: License :: OSI Approved :: MIT License
Classifier: Operating System :: OS Independent
Classifier: Programming Language :: Python
Classifier: Programming Language :: Python :: 3
Classifier: Programming Language :: Python :: 3.9
Classifier: Programming Language :: Python :: 3.10
Classifier: Programming Language :: Python :: 3.11
Classifier: Intended Audience :: Developers
Classifier: Environment :: Web Environment
Classifier: Topic :: Internet
Classifier: License :: OSI Approved :: MIT License
Classifier: Operating System :: OS Independent
Classifier: Programming Language :: Python :: Implementation :: CPython
Classifier: Programming Language :: Python :: Implementation :: PyPy
Requires-Python: >=3.9
License-File: LICENSE
Requires-Dist: tld
Requires-Dist: importlib-metadata ; python_version < "3.8"
